ucdp_addr-1.11.0.dist-info/METADATA
ucdp_addr-1.11.0.dist-info/WHEEL
ucdp_addr-1.11.0.dist-info/entry_points.txt
ucdp_addr-1.11.0.dist-info/licenses/LICENSE
ucdp_addr/__init__.py
ucdp_addr/access.py
ucdp_addr/addrdecoder.py
ucdp_addr/addrinfo.py
ucdp_addr/addrmap.py
ucdp_addr/addrmapfinder.py
ucdp_addr/addrmapref.py
ucdp_addr/addrmaster.py
ucdp_addr/addrmatrix.py
ucdp_addr/addrrange.py
ucdp_addr/addrref.py
ucdp_addr/addrslave.py
ucdp_addr/addrspace.py
ucdp_addr/addrspacealias.py
ucdp_addr/addrspaces.py
ucdp_addr/cli.py
ucdp_addr/const.py
ucdp_addr/data.py
ucdp_addr/datainfo.py
ucdp_addr/defines.py
ucdp_addr/resolver.py
ucdp_addr/util.py
ucdp_addr/wordinfo.py
ucdp_addr-1.11.0.dist-info/RECORD
