Metadata-Version: 2.1
Name: ucdp-addr
Version: 1.11.0
Summary: Unified Chip Design Platform - Address Map
Classifier: Programming Language :: Python :: 3
Classifier: Operating System :: OS Independent
Project-URL: Homepage, https://github.com/nbiotcloud/ucdp-addr
Project-URL: Documentation, https://ucdp-addr.readthedocs.io/en/stable/
Project-URL: Bug Tracker, https://github.com/nbiotcloud/ucdp-addr/issues
Requires-Python: <4.0,>=3.10.0
Requires-Dist: ucdp>=0.27.0
Requires-Dist: ucdp-glbl>=1.4.0
